{
	"Condition Layout Product Page": {
		"prefix": "condlp",
		"description": "VTEXIO - Defines a Condition Layout in Product Page",
		"scope": "jsonc",
		"body": [
			"\"condition-layout.product#${1:cond1}\": {",
			"\t\"props\": {",
			"\t\t\"conditions\": [",
			"\t\t\t{",
			"\t\t\t\t\"toBe\": true, // subject prop must met the predefined conditions to render the new layout",
			"\t\t\t\t\"subject\": \"\", // productId | categoryId | brandId | selectedItemId | productClusters | categoryTree",
			"\t\t\t\t\"arguments\": {",
			"\t\t\t\t\t\"id\": \"\"",
			"\t\t\t\t}",
			"\t\t\t},",
			"\t\t\t{",
			"\t\t\t\t\"toBe\": true,",
			"\t\t\t\t\"subject\": \"specificationProperties\",",
			"\t\t\t\t\"arguments\": {",
			"\t\t\t\t\t\"name\": \"\"",
			"\t\t\t\t\t//\"value\": \"\"",
			"\t\t\t\t}",
			"\t\t\t},",
			"\t\t\t{",
			"\t\t\t\t\"toBe\": true,",
			"\t\t\t\t\"subject\": \"areAllVariationsSelected\"", 
			"\t\t\t},",
			"\t\t\t{",
			"\t\t\t\t\"toBe\": true,",
			"\t\t\t\t\"subject\": \"isProductAvailable\"", 
			"\t\t\t},",
			"\t\t\t{",
			"\t\t\t\t\"toBe\": true,",
			"\t\t\t\t\"subject\": \"hasMoreSellersThan\",",
			"\t\t\t\t\"arguments\": {",
			"\t\t\t\t\t\"quantity\": 0",
			"\t\t\t\t}",
			"\t\t\t}",
			"\t\t]",
			"\t},",
			"\t\"matchType\": \"any\", // any|all|none",
			"\t\"Then\": \"\", // Name of the block to be rendered if the conditions are met.",
			"\t\"Else\": \"\" // Name of the block to be rendered if the conditions are not met.",
			"}"
		]
	},
	"Condition Layout Search": {
		"prefix": "condls",
		"description": "VTEXIO - Defines a Condition Layout in Search Page",
		"scope": "jsonc",
		"body": [
			"\"condition-layout.category#${1:cond1}\": {",
			"\t\"props\": {",
			"\t\t\"conditions\": [",
			"\t\t\t{",
			"\t\t\t\t\"toBe\": true, // subject prop must met the predefined conditions to render the new layout",
			"\t\t\t\t\"subject\": \"\", // department | category",
			"\t\t\t\t\"arguments\": {",
			"\t\t\t\t\t\"ids\": [] // string[]",
			"\t\t\t\t}",
			"\t\t\t}",
			"\t\t]",
			"\t},",
			"\t\"matchType\": \"any\", // any|all|none",
			"\t\"Then\": \"\", // Name of the block to be rendered if the conditions are met.",
			"\t\"Else\": \"\" // Name of the block to be rendered if the conditions are not met.",
			"}"
		]
	},
	"Condition Layout BindingId": {
		"prefix": "condlpb",
		"description": "VTEXIO - Defines a Condition Layout in Product Page BindingId",
		"scope": "jsonc",
		"body": [
			"\"condition-layout.bindingId#${1:cond1}\": {",
			"\t\"props\": {",
			"\t\t\"conditions\": [",
			"\t\t\t{",
			"\t\t\t\t\"toBe\": true, // subject prop must met the predefined conditions to render the new layout",
			"\t\t\t\t\"subject\": \"bindingId\",",
			"\t\t\t\t\"arguments\": {",
			"\t\t\t\t\t\"id\": \"\"",
			"\t\t\t\t}",
			"\t\t\t}",
			"\t\t]",
			"\t},",
			"\t\"matchType\": \"any\", // any|all|none",
			"\t\"Then\": \"\", // Name of the block to be rendered if the conditions are met.",
			"\t\"Else\": \"\" // Name of the block to be rendered if the conditions are not met.",
			"}"
		]
	}
}
